Metadata-Version: 2.1
Name: bitepics
Version: 1.0.0
Summary: AI-powered restaurant location analysis using Google Maps and LLM insights for marketing optimization
Home-page: https://bite.pics
Author: BitePics
Author-email: info@bite.pics
License: UNKNOWN
Project-URL: Homepage, https://bite.pics
Project-URL: Bug Tracker, https://github.com/bitepics/bitepics-python/issues
Project-URL: Repository, https://github.com/bitepics/bitepics-python
Project-URL: Documentation, https://bite.pics/docs
Keywords: restaurant,location,analysis,google-maps,ai,marketing,food-business,llm,bitepics,business-intelligence,geo-analysis,restaurant-marketing,food-photography,ai-enhancement
Platform: UNKNOWN
Classifier: Development Status :: 5 - Production/Stable
Classifier: Intended Audience :: Developers
Classifier: Topic :: Software Development :: Libraries :: Python Modules
Classifier: Topic :: Scientific/Engineering :: Artificial Intelligence
Classifier: Topic :: Internet :: WWW/HTTP :: Indexing/Search
Classifier: Topic :: Office/Business :: Financial :: Point-Of-Sale
Classifier: License :: OSI Approved :: MIT License
Classifier: Programming Language :: Python :: 3
Classifier: Programming Language :: Python :: 3.8
Classifier: Programming Language :: Python :: 3.9
Classifier: Programming Language :: Python :: 3.10
Classifier: Programming Language :: Python :: 3.11
Classifier: Programming Language :: Python :: 3.12
Classifier: Operating System :: OS Independent
Requires-Python: >=3.8
Provides-Extra: dev
Provides-Extra: docs
License-File: LICENSE
